fmeval/COMMIT_HASH
fmeval/__init__.py
fmeval/constants.py
fmeval/data_loaders/__init__.py
fmeval/data_loaders/data_config.py
fmeval/data_loaders/data_sources.py
fmeval/data_loaders/jmespath_util.py
fmeval/data_loaders/json_data_loader.py
fmeval/data_loaders/json_parser.py
fmeval/data_loaders/util.py
fmeval/eval.py
fmeval/eval_algo_mapping.py
fmeval/eval_algorithms/__init__.py
fmeval/eval_algorithms/classification_accuracy.py
fmeval/eval_algorithms/classification_accuracy_semantic_robustness.py
fmeval/eval_algorithms/common.py
fmeval/eval_algorithms/eval_algorithm.py
fmeval/eval_algorithms/factual_knowledge.py
fmeval/eval_algorithms/general_semantic_robustness.py
fmeval/eval_algorithms/helper_models/__init__.py
fmeval/eval_algorithms/helper_models/helper_model.py
fmeval/eval_algorithms/prompt_stereotyping.py
fmeval/eval_algorithms/qa_accuracy.py
fmeval/eval_algorithms/qa_accuracy_semantic_robustness.py
fmeval/eval_algorithms/qa_toxicity.py
fmeval/eval_algorithms/save_strategy.py
fmeval/eval_algorithms/semantic_perturbation_utils.py
fmeval/eval_algorithms/semantic_robustness_utils.py
fmeval/eval_algorithms/summarization_accuracy.py
fmeval/eval_algorithms/summarization_accuracy_semantic_robustness.py
fmeval/eval_algorithms/summarization_toxicity.py
fmeval/eval_algorithms/toxicity.py
fmeval/eval_algorithms/util.py
fmeval/exceptions.py
fmeval/model_runners/__init__.py
fmeval/model_runners/bedrock_model_runner.py
fmeval/model_runners/composers/__init__.py
fmeval/model_runners/composers/composers.py
fmeval/model_runners/composers/jumpstart_composer.py
fmeval/model_runners/composers/template.py
fmeval/model_runners/extractors/__init__.py
fmeval/model_runners/extractors/extractor.py
fmeval/model_runners/extractors/json_extractor.py
fmeval/model_runners/extractors/jumpstart_extractor.py
fmeval/model_runners/model_runner.py
fmeval/model_runners/sm_jumpstart_model_runner.py
fmeval/model_runners/sm_model_runner.py
fmeval/model_runners/util.py
fmeval/perf_util.py
fmeval-1.2.2.dist-info/LICENSE
fmeval-1.2.2.dist-info/METADATA
fmeval-1.2.2.dist-info/NOTICE
fmeval-1.2.2.dist-info/WHEEL
fmeval-1.2.2.dist-info/RECORD
