Metadata-Version: 2.1
Name: fmeval
Version: 1.2.2
Summary: Amazon Foundation Model Evaluations
License: Apache-2.0
Author: Amazon FMEval Team
Author-email: amazon-fmeval-team@amazon.com
Requires-Python: >=3.10,<4.0
Classifier: Development Status :: 1 - Planning
Classifier: Intended Audience :: Developers
Classifier: License :: OSI Approved :: Apache Software License
Classifier: Natural Language :: English
Classifier: Programming Language :: Python
Classifier: Programming Language :: Python :: 3
Classifier: Programming Language :: Python :: 3.10
Classifier: Programming Language :: Python :: 3.11
Classifier: Programming Language :: Python :: 3.12
Requires-Dist: IPython
Requires-Dist: aiohttp (>=3.11.11,<4.0.0)
Requires-Dist: bert-score (>=0.3.13,<0.4.0)
Requires-Dist: evaluate (>=0.4.0,<0.5.0)
Requires-Dist: grpcio (>=1.68.1,<2.0.0)
Requires-Dist: ipykernel (>=6.29.5,<7.0.0)
Requires-Dist: jiwer (>=3.0.5,<4.0.0)
Requires-Dist: markdown
Requires-Dist: matplotlib (>=3.10.0,<4.0.0)
Requires-Dist: mypy-boto3-bedrock (>=1.35.75,<2.0.0)
Requires-Dist: nltk (>=3.9.0,<4.0.0)
Requires-Dist: pandas (==2.2.3)
Requires-Dist: pyarrow
Requires-Dist: pyfunctional (==1.5.0)
Requires-Dist: ray (==2.40.0)
Requires-Dist: rouge-score (>=0.1.2,<0.2.0)
Requires-Dist: sagemaker (>=2.237.1,<3.0.0)
Requires-Dist: scikit-learn (>=1.6.0,<2.0.0)
Requires-Dist: semantic-version (==2.10.0)
Requires-Dist: testbook (>=0.4.2,<0.5.0)
Requires-Dist: torch (>=2.5.0)
Requires-Dist: transformers (>=4.47.0,<5.0.0)
Requires-Dist: urllib3 (>=2.3.0)
